{
    "area": {
        "mbid": {
            "relatable": "overview",
            "multiple": true
        },
        "custom_tabs": ["artists", "labels", "releases", "places"],
        "edit_table": true,
        "merging": true,
        "model": "Area",
        "type": {"simple": true},
        "annotations": {"edit_type": 85},
        "aliases": {
            "add_edit_type": 86,
            "edit_edit_type": 88,
            "delete_edit_type": 87,
            "search_hint_type": 3
        },
        "disambiguation": true,
        "date_period": true,
        "removal": {"manual": true},
        "tags": true,
        "plural": "areas"
    },
    "artist": {
        "mbid": {"relatable": "dedicated", "multiple": true, "indexable": true},
        "custom_tabs": ["releases", "recordings", "works", "events"],
        "edit_table": true,
        "merging": true,
        "model": "Artist",
        "type": {"simple": true},
        "annotations": {"edit_type": 5},
        "aliases": {
            "add_edit_type": 6,
            "edit_edit_type": 8,
            "delete_edit_type": 7,
            "search_hint_type": 3
        },
        "sort_name": true,
        "disambiguation": true,
        "date_period": true,
        "ratings": true,
        "tags": true,
        "subscriptions": {"entity": true, "deleted": true},
        "report_filter": true,
        "collections": true,
        "removal": {
            "automatic": {
                "exempt": [1, 2],
                "extra_fks": {"artist_credit_name": "artist"}
            }
        },
        "plural": "artists",
        "plural_url": "artists",
        "url": "artist",
        "sitemaps_lastmod_table": true
    },
    "event": {
        "mbid": {"relatable": "overview", "multiple": true, "indexable": true},
        "edit_table": true,
        "merging": true,
        "model": "Event",
        "type": { "simple": true },
        "annotations": {"edit_type": 154},
        "aliases": {
            "add_edit_type": 155,
            "edit_edit_type": 157,
            "delete_edit_type": 156,
            "search_hint_type": 2
        },
        "disambiguation": true,
        "date_period": true,
        "ratings": true,
        "tags": true,
        "removal": {"automatic": {}},
        "collections": true,
        "plural": "events",
        "plural_url": "events",
        "url": "event"
    },
    "instrument": {
        "mbid": {"relatable": "overview", "multiple": true, "indexable": true},
        "custom_tabs": ["releases", "recordings"],
        "edit_table": true,
        "merging": true,
        "model": "Instrument",
        "type": {"simple": true},
        "annotations": {"edit_type": 135},
        "aliases": {
            "add_edit_type": 136,
            "edit_edit_type": 138,
            "delete_edit_type": 137,
            "search_hint_type": 2
        },
        "disambiguation": true,
        "removal": {"manual": true},
        "tags": true,
        "plural": "instruments",
        "plural_url": "instruments",
        "url": "instrument"
    },
    "label": {
        "mbid": {"relatable": "dedicated", "multiple": true, "indexable": true},
        "edit_table": true,
        "merging": true,
        "model": "Label",
        "type": {"simple": true},
        "annotations": {"edit_type": 15},
        "aliases": {
            "add_edit_type": 16,
            "edit_edit_type": 18,
            "delete_edit_type": 17,
            "search_hint_type": 2
        },
        "disambiguation": true,
        "date_period": true,
        "ratings": true,
        "tags": true,
        "subscriptions": {"entity": true, "deleted": true},
        "report_filter": true,
        "removal": {
            "manual": true,
            "automatic": {
                "exempt": [1],
                "extra_fks": {"release_label": "label"}
            }
        },
        "plural": "labels",
        "plural_url": "labels",
        "url": "label",
        "sitemaps_lastmod_table": true
    },
    "place": {
        "mbid": {"relatable": "overview", "multiple": true, "indexable": true},
        "custom_tabs": ["events", "performances", "map"],
        "edit_table": true,
        "merging": true,
        "model": "Place",
        "type": {"simple": true},
        "annotations": {"edit_type": 65},
        "aliases": {
            "add_edit_type": 66,
            "edit_edit_type": 68,
            "delete_edit_type": 67,
            "search_hint_type": 2
        },
        "disambiguation": true,
        "date_period": true,
        "tags": true,
        "removal": {"automatic": {}},
        "collections": true,
        "plural": "places",
        "plural_url": "places",
        "url": "place",
        "sitemaps_lastmod_table": true
    },
    "recording": {
        "mbid": {"relatable": "overview", "multiple": true},
        "custom_tabs": ["fingerprints"],
        "edit_table": true,
        "merging": true,
        "model": "Recording",
        "annotations": {"edit_type": 75},
        "aliases": {
            "add_edit_type": 711,
            "edit_edit_type": 713,
            "delete_edit_type": 712,
            "search_hint_type": 2
        },
        "disambiguation": true,
        "ratings": true,
        "tags": true,
        "artist_credits": true,
        "report_filter": true,
        "collections": true,
        "removal": {"manual": true},
        "plural": "recordings",
        "plural_url": "recordings",
        "url": "recording",
        "sitemaps_lastmod_table": true
    },
    "release": {
        "mbid": {"relatable": "overview", "multiple": true, "indexable": true},
        "custom_tabs": ["discids", "cover_art"],
        "edit_table": true,
        "merging": true,
        "model": "Release",
        "annotations": {"edit_type": 35},
        "aliases": {
            "add_edit_type": 318,
            "edit_edit_type": 320,
            "delete_edit_type": 319,
            "search_hint_type": 2
        },
        "disambiguation": true,
        "tags": true,
        "artist_credits": true,
        "removal": {"manual": true},
        "report_filter": true,
        "collections": true,
        "plural": "releases",
        "plural_url": "releases",
        "url": "release",
        "sitemaps_lastmod_table": true
    },
    "release_group": {
        "mbid": {"relatable": "overview", "multiple": true, "indexable": true},
        "edit_table": true,
        "merging": true,
        "model": "ReleaseGroup",
        "type": {"complex": true},
        "annotations": {"edit_type": 25},
        "aliases": {
            "add_edit_type": 26,
            "edit_edit_type": 28,
            "delete_edit_type": 27,
            "search_hint_type": 2
        },
        "disambiguation": true,
        "ratings": true,
        "tags": true,
        "artist_credits": true,
        "report_filter": true,
        "removal": {
            "automatic": {
                "extra_fks": {"release": "release_group"}
            }
        },
        "plural": "release_groups",
        "plural_url": "release-groups",
        "url": "release-group",
        "sitemaps_lastmod_table": true
    },
    "series": {
        "mbid": {"relatable": "overview", "multiple": true, "indexable": true},
        "edit_table": true,
        "merging": true,
        "model": "Series",
        "type": {"simple": true},
        "plural": "series",
        "plural_url": "series",
        "url": "series",
        "annotations": {"edit_type": 144},
        "aliases": {
            "add_edit_type": 145,
            "edit_edit_type": 147,
            "delete_edit_type": 146,
            "search_hint_type": 2
        },
        "disambiguation": true,
        "subscriptions": {"entity": true, "deleted": true},
        "report_filter": true,
        "removal": {"automatic": {}},
        "tags": true
    },
    "url": {
        "mbid": {"relatable": "overview", "multiple": true, "no_details": true},
        "edit_table": true,
        "model": "URL",
        "plural": "urls",
        "plural_url": "urls",
        "url": "url"
    },
    "work": {
        "mbid": {"relatable": "overview", "multiple": true, "indexable": true},
        "edit_table": true,
        "sitemaps_lastmod_table": true,
        "merging": true,
        "model": "Work",
        "type": {"simple": true},
        "annotations": {"edit_type": 45},
        "aliases": {
            "add_edit_type": 46,
            "edit_edit_type": 48,
            "delete_edit_type": 47,
            "search_hint_type": 2
        },
        "disambiguation": true,
        "ratings": true,
        "tags": true,
        "report_filter": true,
        "removal": {"automatic": {}},
        "collections": true,
        "plural": "works",
        "plural_url": "works",
        "url": "work"
    },
    "track": {
        "mbid": {"multiple": true},
        "model": "Track",
        "artist_credits": 1
    },
    "editor": {
        "model": "Editor",
        "subscriptions": {"entity": false}
    },
    "collection": {
        "mbid": {"relatable": false},
        "table": "editor_collection",
        "model": "Collection",
        "subscriptions": {"entity": true}
    },
    "cdstub": {
        "model": "CDStub"
    },
    "annotation": {
        "model": "Annotation"
    },
    "isrc": {
        "model": "ISRC"
    },
    "iswc": {
        "model": "ISWC"
    },
    "freedb": {
        "model": "FreeDB"
    },
    "tag": {
        "model": "Tag"
    }
}
